[{"Set" : "POP Series Promo 1","Year" : "2004","Total Cards" : "17","Abbreviation" : "P1","TCGP Group" : "1422","TCGP Abbreviation" : "POP"},{"Set" : "POP Series Promo 2","Year" : "2005","Total Cards" : "17","Abbreviation" : "P2","TCGP Group" : "1447","TCGP Abbreviation" : "POP"},{"Set" : "POP Series Promo 3","Year" : "2006","Total Cards" : "17","Abbreviation" : "P3","TCGP Group" : "1442","TCGP Abbreviation" : "POP"},{"Set" : "POP Series Promo 4","Year" : "2006","Total Cards" : "17","Abbreviation" : "P4","TCGP Group" : "1452","TCGP Abbreviation" : "POP"},{"Set" : "POP Series Promo 5","Year" : "2007","Total Cards" : "17","Abbreviation" : "P5","TCGP Group" : "1439","TCGP Abbreviation" : "POP"},{"Set" : "POP Series Promo 6","Year" : "2007","Total Cards" : "17","Abbreviation" : "P6","TCGP Group" : "1432","TCGP Abbreviation" : "POP"},{"Set" : "POP Series Promo 7","Year" : "2008","Total Cards" : "17","Abbreviation" : "P7","TCGP Group" : "1414","TCGP Abbreviation" : "POP"},{"Set" : "POP Series Promo 8","Year" : "2008","Total Cards" : "17","Abbreviation" : "P8","TCGP Group" : "1450","TCGP Abbreviation" : "POP"},{"Set" : "POP Series Promo 9","Year" : "2009","Total Cards" : "17","Abbreviation" : "P9","TCGP Group" : "1446","TCGP Abbreviation" : "POP"}]