[{"Pokedex" : "Noivern","Pokemon" : "","Type" : "","Rarity" : "","HoloFoil" : "","Rarity Extra" : "","Set No." : "","Set" : "","Artist" : "","Damaged" : "","Price" : ""},{"Pokedex" : "711","Pokemon" : "Gourgeist","Type" : "P","Rarity" : "","HoloFoil" : "","Rarity Extra" : "","Set No." : "2/30","Set" : "N","Artist" : "5ban Graphics","Damaged" : "","Price" : ""},{"Pokedex" : "24","Pokemon" : "Arbok","Type" : "P","Rarity" : "3","HoloFoil" : "","Rarity Extra" : "","Set No." : "Fri Mar 30 2018 00:00:00 GMT-0400 (EDT)","Set" : "N","Artist" : "Naoki Saito","Damaged" : "","Price" : "2.56"},{"Pokedex" : "659","Pokemon" : "Bunnelby","Type" : "N","Rarity" : "","HoloFoil" : "","Rarity Extra" : "","Set No." : "Mon Apr 30 2018 00:00:00 GMT-0400 (EDT)","Set" : "N","Artist" : "5ban Graphics","Damaged" : "","Price" : ""},{"Pokedex" : "710","Pokemon" : "Pumpkaboo","Type" : "P","Rarity" : "","HoloFoil" : "","Rarity Extra" : "","Set No." : "Fri Nov 30 2018 00:00:00 GMT-0500 (EST)","Set" : "N","Artist" : "5ban Graphics","Damaged" : "","Price" : ""},{"Pokedex" : "T","Pokemon" : "Potion","Type" : "I","Rarity" : "","HoloFoil" : "","Rarity Extra" : "","Set No." : "15/30","Set" : "N","Artist" : "5ban Graphics","Damaged" : "","Price" : ""},{"Pokedex" : "23","Pokemon" : "Ekans","Type" : "P","Rarity" : "1","HoloFoil" : "","Rarity Extra" : "","Set No." : "16/30","Set" : "N","Artist" : "Shigenori Negishi","Damaged" : "","Price" : "2.19"},{"Pokedex" : "676","Pokemon" : "Forfrou","Type" : "N","Rarity" : "","HoloFoil" : "","Rarity Extra" : "","Set No." : "20/30","Set" : "N","Artist" : "5ban Graphics","Damaged" : "","Price" : ""},{"Pokedex" : "T","Pokemon" : "Poke Ball","Type" : "I","Rarity" : "","HoloFoil" : "","Rarity Extra" : "","Set No." : "21/30","Set" : "N","Artist" : "5ban Graphics","Damaged" : "","Price" : ""},{"Pokedex" : "714","Pokemon" : "Noibat","Type" : "N","Rarity" : "","HoloFoil" : "","Rarity Extra" : "","Set No." : "23/30","Set" : "N","Artist" : "5ban Graphics","Damaged" : "","Price" : ""},{"Pokedex" : "T","Pokemon" : "Dark Energy","Type" : "E","Rarity" : "","HoloFoil" : "","Rarity Extra" : "","Set No." : "28/30","Set" : "N","Artist" : "","Damaged" : "","Price" : ""},{"Pokedex" : "715","Pokemon" : "Noivern","Type" : "Dr","Rarity" : "","HoloFoil" : "","Rarity Extra" : "","Set No." : "30/30","Set" : "N","Artist" : "5ban Graphics","Damaged" : "","Price" : ""},{"Pokedex" : "Sylveon","Pokemon" : "","Type" : "","Rarity" : "","HoloFoil" : "","Rarity Extra" : "","Set No." : "","Set" : "","Artist" : "","Damaged" : "","Price" : ""},{"Pokedex" : "T","Pokemon" : "Switch","Type" : "I","Rarity" : "","HoloFoil" : "","Rarity Extra" : "","Set No." : "Tue Apr 30 2019 00:00:00 GMT-0400 (EDT)","Set" : "S","Artist" : "5ban Graphics","Damaged" : "","Price" : ""},{"Pokedex" : "676","Pokemon" : "Forfrou","Type" : "N","Rarity" : "","HoloFoil" : "","Rarity Extra" : "","Set No." : "16/30","Set" : "S","Artist" : "5ban Graphics","Damaged" : "","Price" : ""},{"Pokedex" : "T","Pokemon" : "Fairy Energy","Type" : "E","Rarity" : "","HoloFoil" : "","Rarity Extra" : "","Set No." : "18/30","Set" : "S","Artist" : "","Damaged" : "","Price" : ""},{"Pokedex" : "661","Pokemon" : "Fletchling","Type" : "N","Rarity" : "","HoloFoil" : "","Rarity Extra" : "","Set No." : "19/30","Set" : "S","Artist" : "5ban Graphics","Damaged" : "","Price" : ""},{"Pokedex" : "T","Pokemon" : "Pokemon Catcher","Type" : "I","Rarity" : "","HoloFoil" : "","Rarity Extra" : "","Set No." : "23/30","Set" : "S","Artist" : "5ban Graphics","Damaged" : "","Price" : ""},{"Pokedex" : "209","Pokemon" : "Snubbull","Type" : "Fa","Rarity" : "","HoloFoil" : "","Rarity Extra" : "","Set No." : "27/30","Set" : "S","Artist" : "Naoki Saito","Damaged" : "","Price" : ""},{"Pokedex" : "210","Pokemon" : "Granbull","Type" : "Fa","Rarity" : "","HoloFoil" : "","Rarity Extra" : "","Set No." : "29/30","Set" : "S","Artist" : "Masokazu Fukuda","Damaged" : "","Price" : ""},{"Pokedex" : "700","Pokemon" : "Sylveon","Type" : "Fa","Rarity" : "","HoloFoil" : "","Rarity Extra" : "","Set No." : "30/30","Set" : "S","Artist" : "5ban Graphics","Damaged" : "","Price" : ""},{"Pokedex" : "Zoroark","Pokemon" : "","Type" : "","Rarity" : "","HoloFoil" : "","Rarity Extra" : "","Set No." : "","Set" : "","Artist" : "","Damaged" : "","Price" : ""},{"Pokedex" : "509","Pokemon" : "Purrloin","Type" : "D","Rarity" : "","HoloFoil" : "","Rarity Extra" : "","Set No." : "Tue Jan 30 2018 00:00:00 GMT-0500 (EST)","Set" : "Z","Artist" : "Kagemaru Himeno","Damaged" : "","Price" : ""},{"Pokedex" : "505","Pokemon" : "Watchog","Type" : "N","Rarity" : "","HoloFoil" : "","Rarity Extra" : "","Set No." : "2/30","Set" : "Z","Artist" : "match","Damaged" : "","Price" : ""},{"Pokedex" : "T","Pokemon" : "PlusPower","Type" : "I","Rarity" : "","HoloFoil" : "","Rarity Extra" : "","Set No." : "Sat Nov 30 2019 00:00:00 GMT-0500 (EST)","Set" : "Z","Artist" : "5ban Graphics","Damaged" : "","Price" : ""},{"Pokedex" : "570","Pokemon" : "Zorua","Type" : "D","Rarity" : "","HoloFoil" : "","Rarity Extra" : "","Set No." : "13/30","Set" : "Z","Artist" : "Kouki Saitou","Damaged" : "","Price" : ""},{"Pokedex" : "571","Pokemon" : "Zoroark","Type" : "D","Rarity" : "","HoloFoil" : "","Rarity Extra" : "","Set No." : "17/30","Set" : "Z","Artist" : "Shin Nagasawa","Damaged" : "","Price" : ""},{"Pokedex" : "Excadrill","Pokemon" : "","Type" : "","Rarity" : "","HoloFoil" : "","Rarity Extra" : "","Set No." : "","Set" : "","Artist" : "","Damaged" : "","Price" : ""},{"Pokedex" : "T","Pokemon" : "Energy Switch","Type" : "I","Rarity" : "","HoloFoil" : "","Rarity Extra" : "","Set No." : "Tue Apr 30 2019 00:00:00 GMT-0400 (EDT)","Set" : "E","Artist" : "Kent Kanetsuna","Damaged" : "","Price" : ""},{"Pokedex" : "533","Pokemon" : "Gurdurr","Type" : "Fg","Rarity" : "","HoloFoil" : "","Rarity Extra" : "","Set No." : "14/30","Set" : "E","Artist" : "Naoki Saito","Damaged" : "","Price" : ""},{"Pokedex" : "T","Pokemon" : "Potion","Type" : "I","Rarity" : "","HoloFoil" : "","Rarity Extra" : "","Set No." : "15/30","Set" : "E","Artist" : "Ayaka Yoshida","Damaged" : "","Price" : ""},{"Pokedex" : "530","Pokemon" : "Excadrill","Type" : "Fg","Rarity" : "","HoloFoil" : "","Rarity Extra" : "","Set No." : "17/30","Set" : "E","Artist" : "5ban Graphics","Damaged" : "","Price" : ""},{"Pokedex" : "507","Pokemon" : "Herdier","Type" : "N","Rarity" : "","HoloFoil" : "","Rarity Extra" : "","Set No." : "19/30","Set" : "E","Artist" : "Midori Harada","Damaged" : "","Price" : ""},{"Pokedex" : "Lucario","Pokemon" : "","Type" : "","Rarity" : "","HoloFoil" : "","Rarity Extra" : "","Set No." : "","Set" : "","Artist" : "","Damaged" : "","Price" : ""},{"Pokedex" : "66","Pokemon" : "Machop","Type" : "Fg","Rarity" : "","HoloFoil" : "","Rarity Extra" : "","Set No." : "Fri May 11 2018 00:00:00 GMT-0400 (EDT)","Set" : "L","Artist" : "Atsuko Nishida","Damaged" : "","Price" : ""},{"Pokedex" : "Manaphy","Pokemon" : "","Type" : "","Rarity" : "","HoloFoil" : "","Rarity Extra" : "","Set No." : "","Set" : "","Artist" : "","Damaged" : "","Price" : ""},{"Pokedex" : "419","Pokemon" : "Floatzel","Type" : "W","Rarity" : "","HoloFoil" : "","Rarity Extra" : "","Set No." : "Mon Feb 12 2018 00:00:00 GMT-0500 (EST)","Set" : "Ma","Artist" : "Masahiko Ishii","Damaged" : "","Price" : ""},{"Pokedex" : "118","Pokemon" : "Goldeen","Type" : "W","Rarity" : "","HoloFoil" : "","Rarity Extra" : "","Set No." : "Mon Mar 12 2018 00:00:00 GMT-0400 (EDT)","Set" : "Ma","Artist" : "Atsuko Nishida","Damaged" : "","Price" : ""},{"Pokedex" : "490","Pokemon" : "Manaphy","Type" : "W","Rarity" : "","HoloFoil" : "Art","Rarity Extra" : "","Set No." : "Thu Apr 12 2018 00:00:00 GMT-0400 (EDT)","Set" : "Ma","Artist" : "Daisuke Ito","Damaged" : "","Price" : ""},{"Pokedex" : "Plusle","Pokemon" : "","Type" : "","Rarity" : "","HoloFoil" : "","Rarity Extra" : "","Set No." : "","Set" : "","Artist" : "","Damaged" : "","Price" : ""},{"Pokedex" : "325","Pokemon" : "Spoink","Type" : "P","Rarity" : "","HoloFoil" : "","Rarity Extra" : "","Set No." : "Thu Jul 12 2018 00:00:00 GMT-0400 (EDT)","Set" : "P","Artist" : "Kagemaru Himeno","Damaged" : "","Price" : ""},{"Pokedex" : "Minun","Pokemon" : "","Type" : "","Rarity" : "","HoloFoil" : "","Rarity Extra" : "","Set No." : "","Set" : "","Artist" : "","Damaged" : "","Price" : ""},{"Pokedex" : "Latias","Pokemon" : "","Type" : "","Rarity" : "","HoloFoil" : "","Rarity Extra" : "","Set No." : "","Set" : "","Artist" : "","Damaged" : "","Price" : ""},{"Pokedex" : "255","Pokemon" : "Torchic","Type" : "F","Rarity" : "","HoloFoil" : "","Rarity Extra" : "","Set No." : "Tue Jul 10 2018 00:00:00 GMT-0400 (EDT)","Set" : "La","Artist" : "Hironobu Yoshida","Damaged" : "Yes","Price" : ""}]